primate/__init__.py
primate/decision/__init__.py
primate/decision/agent.py
primate/decision/environment.py
primate/decision/strategy.py
primate/nlp/__init__.py
primate/nlp/embedding.py
primate/nlp/preprocessing.py
primate/nlp/sentiment.py
primate/nlp/tokenizer.py
primate/nlp/vectorizer.py
primate/utils/__init__.py
primate/utils/helpers.py
primate-0.2.0.dist-info/LICENSE.txt
primate-0.2.0.dist-info/METADATA
primate-0.2.0.dist-info/WHEEL
primate-0.2.0.dist-info/top_level.txt
primate-0.2.0.dist-info/RECORD
