Metadata-Version: 2.1
Name: primate
Version: 0.2.0
Summary: Primate AI: Tools for decision-making and NLP.
Author: Mathis Daviau
Classifier: Development Status :: 4 - Beta
Classifier: Intended Audience :: Developers
Classifier: Programming Language :: Python :: 3
Classifier: Programming Language :: Python :: 3.7
Classifier: Programming Language :: Python :: 3.8
Classifier: Programming Language :: Python :: 3.9
Classifier: License :: OSI Approved :: MIT License
Classifier: Operating System :: OS Independent
Requires-Python: >=3.7
License-File: LICENSE.txt
Requires-Dist: numpy>=1.21.0
Requires-Dist: matplotlib>=3.4.0
Requires-Dist: torch>=1.9.0
Requires-Dist: transformers>=4.0.0
Requires-Dist: scikit-learn>=0.24.0
Requires-Dist: pyyaml>=5.4.0
Provides-Extra: dev
Requires-Dist: pytest>=6.2.0; extra == "dev"
Requires-Dist: flake8>=3.9.0; extra == "dev"
